tesla/__init__.py
tesla/admin/__init__.py
tesla/admin/collections.py
tesla/admin/forms.py
tesla/admin/middleware.py
tesla/admin/models.py
tesla/admin/urls.py
tesla/admin/views.py
tesla/admin/statics/__
tesla/admin/statics/admin/assets/.DS_Store
tesla/admin/statics/admin/assets/css/.DS_Store
tesla/admin/statics/admin/assets/css/portal.css
tesla/admin/statics/admin/assets/images/.DS_Store
tesla/admin/statics/admin/assets/js/.DS_Store
tesla/admin/statics/admin/assets/js/app.js
tesla/admin/templates/__init__.py
tesla/admin/templates/admin/__init__.py
tesla/admin/templates/admin/account.html
tesla/admin/templates/admin/base_admin.html
tesla/admin/templates/admin/col.html
tesla/admin/templates/admin/col_n.html
tesla/admin/templates/admin/colls.html
tesla/admin/templates/admin/login.html
tesla/admin/templates/admin/obj copy.html
tesla/admin/templates/admin/obj.html
tesla/admin/templates/admin/register.html
tesla/admin/templates/admin/reset-password.html
tesla/auth/__init__.py
tesla/auth/decorators.py
tesla/auth/forms.py
tesla/auth/modal.py
tesla/auth/views.py
tesla/context/__init__.py
tesla/database/__init__.py
tesla/database/SQL/__init__.py
tesla/database/jsondb/__init__.py
tesla/database/jsondb/schema.py
tesla/database/localdb/__init__.py
tesla/exceptions/__init__.py
tesla/form/__init__.py
tesla/functions/__init__.py
tesla/media/__init__.py
tesla/messages/__init__.py
tesla/middleware/__init__.py
tesla/middleware/auth.py
tesla/modal/__init__.py
tesla/pages/__init__.py
tesla/pagination/__init__.py
tesla/pyhtml/__init__.py
tesla/pyhtml/formater.py
tesla/pyhtml/js.py
tesla/pyhtml/server.py
tesla/pyhtml/tags.py
tesla/pyhtml/watcher.py
tesla/request/__init__.py
tesla/response/__init__.py
tesla/router/__init__.py
tesla/router/url.py
tesla/search/__init__.py
tesla/serializer/__init__.py
tesla/session/__init__.py
tesla/signal/__init__.py
tesla/static/__init__.py
tesla/task/__init__.py
tesla/utils/__init__.py
tesla/views/__init__.py
tesla_web2-0.0.2.dist-info/METADATA
tesla_web2-0.0.2.dist-info/WHEEL
tesla_web2-0.0.2.dist-info/top_level.txt
tesla_web2-0.0.2.dist-info/RECORD
